migrate/__init__.py
migrate/cli.py
migrate/migration.py
migrate/runners/__init__.py
migrate/runners/postgres.py
tests/runners/__init__.py
tests/runners/__init__.pyc
tests/runners/conftest.py
tests/runners/conftest.pyc
tests/runners/test_postgres.py
tests/runners/__pycache__/test_postgres.cpython-27-PYTEST.pyc
trek/__init__.py
trek/cli.py
trek/migration.py
trek/runners/__init__.py
trek/runners/postgres.py
trek-0.0.1_.dist-info/DESCRIPTION.rst
trek-0.0.1_.dist-info/entry_points.txt
trek-0.0.1_.dist-info/METADATA
trek-0.0.1_.dist-info/metadata.json
trek-0.0.1_.dist-info/RECORD
trek-0.0.1_.dist-info/top_level.txt
trek-0.0.1_.dist-info/WHEEL
