Metadata-Version: 2.0
Name: trek
Version: 0.0.1-
Summary: generic migration provider
Home-page: https://github.com/brianhicks/trek
Author: Brian Hicks
Author-email: brian@brianthicks.com
License: 0.0.1
